pymsym-0.3.4.dist-info/METADATA
pymsym-0.3.4.dist-info/RECORD
pymsym-0.3.4.dist-info/entry_points.txt
pymsym-0.3.4.dist-info/WHEEL
pymsym-0.3.4.dist-info/licenses/LICENSE
pymsym/pymsym.py
pymsym/high_level.py
pymsym/libpymsym.so
pymsym/__init__.py
pymsym/.gitignore
