Metadata-Version: 2.1
Name: pymsym
Version: 0.3.4
Summary: libmsym python binding
Keywords: symmetry,molecules,chemistry
Author-Email: Corin Wagen <corinwagen@gmail.com>
License: The MIT License (MIT)
Classifier: Programming Language :: Python :: 3
Classifier: License :: OSI Approved :: MIT License
Classifier: Operating System :: OS Independent
Project-URL: Homepage, https://github.com/corinwagen/pymsym
Requires-Python: >=3.9
Provides-Extra: extra-deps
Requires-Dist: numpy>=1.19.2; extra == "extra-deps"
